psl_dns/__init__.py
psl_dns/base.py
psl_dns/checker.py
psl_dns/exceptions.py
psl_dns/parser.py
psl_dns/querier.py
psl_dns/utils.py
psl_dns/commands/__init__.py
psl_dns/commands/check.py
psl_dns/commands/parse.py
psl_dns/commands/query.py
psl_dns/providers/__init__.py
psl_dns/providers/desec.py
psl_dns/tests/__init__.py
psl_dns/tests/test_querier.py
psl_dns-1.1.1.dist-info/LICENSE
psl_dns-1.1.1.dist-info/METADATA
psl_dns-1.1.1.dist-info/WHEEL
psl_dns-1.1.1.dist-info/entry_points.txt
psl_dns-1.1.1.dist-info/top_level.txt
psl_dns-1.1.1.dist-info/RECORD
