Metadata-Version: 2.1
Name: psl-dns
Version: 1.1.1
Summary: Query the Public Suffix List (PSL) via DNS and check the PSL status of a domain.
Home-page: https://github.com/sse-secure-systems/psl-dns
Author: Peter Thomassen
Author-email: peter.thomassen@securesystems.de
Classifier: Development Status :: 5 - Production/Stable
Classifier: Intended Audience :: Developers
Classifier: Programming Language :: Python :: 3
Classifier: License :: OSI Approved :: MIT License
Classifier: Topic :: Internet :: Name Service (DNS)
License-File: LICENSE
Requires-Dist: dnspython >=1.14.0
Requires-Dist: requests >=2.22.0
